traffic_light_controller.v
module traffic_light_controller (
    input clk,
    input reset,
    output reg [1:0] ns_light,
    output reg [1:0] ew_light
);

    // State encoding using parameters
    parameter NS_GREEN  = 2'b00;
    parameter NS_YELLOW = 2'b01;
    parameter EW_GREEN  = 2'b10;
    parameter EW_YELLOW = 2'b11;

    reg [1:0] state;
    reg [2:0] counter;

    always @(posedge clk or posedge reset) begin
        if (reset) begin
            state <= NS_GREEN;
            counter <= 3'd0;
        end else begin
            if ((state == NS_GREEN || state == EW_GREEN) && counter == 3'd4) begin
                if (state == NS_GREEN)
                    state <= NS_YELLOW;
                else
                    state <= EW_YELLOW;
                counter <= 3'd0;
            end else if ((state == NS_YELLOW || state == EW_YELLOW) && counter == 3'd1) begin
                if (state == NS_YELLOW)
                    state <= EW_GREEN;
                else
                    state <= NS_GREEN;
                counter <= 3'd0;
            end else begin
                counter <= counter + 1;
            end
        end
    end

    always @(*) begin
        case (state)
            NS_GREEN: begin
                ns_light = 2'b10;
                ew_light = 2'b00;
            end
            NS_YELLOW: begin
                ns_light = 2'b01;
                ew_light = 2'b00;
            end
            EW_GREEN: begin
                ns_light = 2'b00;
                ew_light = 2'b10;
            end
            EW_YELLOW: begin
                ns_light = 2'b00;
                ew_light = 2'b01;
            end
            default: begin
                ns_light = 2'b00;
                ew_light = 2'b00;
            end
        endcase
    end

endmodule

tb_traffic_light.v
`timescale 1ns/1ps

module tb_traffic_light;

    reg clk;
    reg reset;
    wire [1:0] ns_light;
    wire [1:0] ew_light;

    traffic_light_controller uut (
        .clk(clk),
        .reset(reset),
        .ns_light(ns_light),
        .ew_light(ew_light)
    );

    initial begin
        clk = 0;
        forever #5 clk = ~clk;
    end

    initial begin
        $dumpfile("output_waveform.vcd");
        $dumpvars(0, tb_traffic_light);

        $display("Time\tNS\tEW");
        $monitor("%0t\t%b\t%b", $time, ns_light, ew_light);

        reset = 1;
        #10;
        reset = 0;

        #200;

        $finish;
    end

endmodule

output_waveform.vcd
$date
	Wed Jul 16 15:45:20 2025
$end
$version
	Icarus Verilog
$end
$timescale
	1ps
$end
$scope module tb_traffic_light $end
$var wire 2 ! ns_light [1:0] $end
$var wire 2 " ew_light [1:0] $end
$var reg 1 # clk $end
$var reg 1 $ reset $end
$scope module uut $end
$var wire 1 # clk $end
$var wire 1 $ reset $end
$var reg 3 % counter [2:0] $end
$var reg 2 & ew_light [1:0] $end
$var reg 2 ' ns_light [1:0] $end
$var reg 2 ( state [1:0] $end
$upscope $end
$upscope $end
$enddefinitions $end
#0
$dumpvars
b0 (
b10 '
b0 &
b0 %
1$
0#
b0 "
b10 !
$end
#5000
1#
#10000
0#
0$
#15000
b1 %
1#
#20000
0#
#25000
b10 %
1#
#30000
0#
#35000
b11 %
1#
#40000
0#
#45000
b100 %
1#
#50000
0#
#55000
b1 !
b1 '
b0 %
b1 (
1#
#60000
0#
#65000
b1 %
1#
#70000
0#
#75000
b10 "
b10 &
b0 !
b0 '
b0 %
b10 (
1#
#80000
0#
#85000
b1 %
1#
#90000
0#
#95000
b10 %
1#
#100000
0#
#105000
b11 %
1#
#110000
0#
#115000
b100 %
1#
#120000
0#
#125000
b1 "
b1 &
b0 %
b11 (
1#
#130000
0#
#135000
b1 %
1#
#140000
0#
#145000
b0 "
b0 &
b10 !
b10 '
b0 %
b0 (
1#
#150000
0#
#155000
b1 %
1#
#160000
0#
#165000
b10 %
1#
#170000
0#
#175000
b11 %
1#
#180000
0#
#185000
b100 %
1#
#190000
0#
#195000
b1 !
b1 '
b0 %
b1 (
1#
#200000
0#
#205000
b1 %
1#
